Metadata-Version: 2.1
Name: HKH-test-Bot
Version: 0.0.8
Summary: Let's make chatbots !
Home-page: UNKNOWN
Author: HKH
Author-email: 
License: UNKNOWN
Keywords: orange3 add-on
Platform: UNKNOWN
